pkg/__init__.py
mlaas_client-0.0.1.dist-info/LICENSE
mlaas_client-0.0.1.dist-info/METADATA
mlaas_client-0.0.1.dist-info/WHEEL
mlaas_client-0.0.1.dist-info/top_level.txt
mlaas_client-0.0.1.dist-info/RECORD
