Metadata-Version: 2.1
Name: mlaas-client
Version: 0.0.1
Summary: ML as a service toolkit
Home-page: https://github.com/pypa/sampleproject
Author: Dvir Ginzburg
Author-email: dvirginz@gmail.com
License: UNKNOWN
Project-URL: Bug Tracker, https://github.com/pypa/sampleproject/issues
Platform: UNKNOWN
Classifier: Programming Language :: Python :: 3
Classifier: License :: OSI Approved :: MIT License
Classifier: Operating System :: OS Independent
Requires-Python: >=3.6
License-File: LICENSE
